gcsutils/__init__.py
gcsutils/gcs.py
gcsutils-2.1.0.dist-info/LICENSE
gcsutils-2.1.0.dist-info/METADATA
gcsutils-2.1.0.dist-info/WHEEL
gcsutils-2.1.0.dist-info/top_level.txt
gcsutils-2.1.0.dist-info/RECORD
