Metadata-Version: 2.1
Name: gcsutils
Version: 2.1.0
Summary: Utility functions for Google Cloud Storage
Home-page: https://github.com/CoralMapping/proc_gcs_utils
Classifier: Programming Language :: Python :: 3
Classifier: License :: OSI Approved :: Apache Software License
Classifier: Operating System :: OS Independent
Requires-Python: >=3.10
License-File: LICENSE
Requires-Dist: google-cloud-storage (==2.4.0)
